{"schema_version":"1.0.0","task_id":"secretscan","entries":[{"task_id":"secretscan","type":"secretscan","timestamp":"2026-04-13T22:03:54.109Z","agent":"pre_check_batch","verdict":"pass","summary":"Secretscan: 0 finding(s), 1 files scanned, 0 skipped","findings_count":0,"scan_directory":"/Users/butze/Documents/git/image-age-sorter","files_scanned":1,"skipped_files":0},{"task_id":"secretscan","type":"secretscan","timestamp":"2026-04-13T22:14:03.726Z","agent":"pre_check_batch","verdict":"pass","summary":"Secretscan: 0 finding(s), 2 files scanned, 0 skipped","findings_count":0,"scan_directory":"/Users/butze/Documents/git/image-age-sorter","files_scanned":2,"skipped_files":0},{"task_id":"secretscan","type":"secretscan","timestamp":"2026-04-13T22:20:22.119Z","agent":"pre_check_batch","verdict":"pass","summary":"Secretscan: 0 finding(s), 1 files scanned, 0 skipped","findings_count":0,"scan_directory":"/Users/butze/Documents/git/image-age-sorter","files_scanned":1,"skipped_files":0},{"task_id":"secretscan","type":"secretscan","timestamp":"2026-04-13T22:45:28.620Z","agent":"pre_check_batch","verdict":"pass","summary":"Secretscan: 0 finding(s), 1 files scanned, 0 skipped","findings_count":0,"scan_directory":"/Users/butze/Documents/git/image-age-sorter","files_scanned":1,"skipped_files":0},{"task_id":"secretscan","type":"secretscan","timestamp":"2026-04-13T23:08:57.166Z","agent":"pre_check_batch","verdict":"pass","summary":"Secretscan: 0 finding(s), 1 files scanned, 0 skipped","findings_count":0,"scan_directory":"/Users/butze/Documents/git/image-age-sorter","files_scanned":1,"skipped_files":0},{"task_id":"secretscan","type":"secretscan","timestamp":"2026-04-13T23:27:50.911Z","agent":"pre_check_batch","verdict":"pass","summary":"Secretscan: 0 finding(s), 1 files scanned, 0 skipped","findings_count":0,"scan_directory":"/Users/butze/Documents/git/image-age-sorter","files_scanned":1,"skipped_files":0},{"task_id":"secretscan","type":"secretscan","timestamp":"2026-04-14T06:26:10.868Z","agent":"pre_check_batch","verdict":"pass","summary":"Secretscan: 0 finding(s), 1 files scanned, 0 skipped","findings_count":0,"scan_directory":"/Users/butze/Documents/git/image-age-sorter","files_scanned":1,"skipped_files":0},{"task_id":"secretscan","type":"secretscan","timestamp":"2026-04-14T06:38:19.518Z","agent":"pre_check_batch","verdict":"pass","summary":"Secretscan: 0 finding(s), 1 files scanned, 0 skipped","findings_count":0,"scan_directory":"/Users/butze/Documents/git/image-age-sorter","files_scanned":1,"skipped_files":0},{"task_id":"secretscan","type":"secretscan","timestamp":"2026-04-14T06:59:01.736Z","agent":"pre_check_batch","verdict":"pass","summary":"Secretscan: 0 finding(s), 1 files scanned, 0 skipped","findings_count":0,"scan_directory":"/Users/butze/Documents/git/image-age-sorter","files_scanned":1,"skipped_files":0},{"task_id":"secretscan","type":"secretscan","timestamp":"2026-04-14T07:35:00.211Z","agent":"pre_check_batch","verdict":"pass","summary":"Secretscan: 0 finding(s), 1 files scanned, 0 skipped","findings_count":0,"scan_directory":"/Users/butze/Documents/git/image-age-sorter","files_scanned":1,"skipped_files":0},{"task_id":"secretscan","type":"secretscan","timestamp":"2026-04-14T07:44:30.501Z","agent":"pre_check_batch","verdict":"pass","summary":"Secretscan: 0 finding(s), 1 files scanned, 0 skipped","findings_count":0,"scan_directory":"/Users/butze/Documents/git/image-age-sorter","files_scanned":1,"skipped_files":0},{"task_id":"secretscan","type":"secretscan","timestamp":"2026-04-14T07:58:44.854Z","agent":"pre_check_batch","verdict":"pass","summary":"Secretscan: 0 finding(s), 1 files scanned, 0 skipped","findings_count":0,"scan_directory":"/Users/butze/Documents/git/image-age-sorter","files_scanned":1,"skipped_files":0},{"task_id":"secretscan","type":"secretscan","timestamp":"2026-04-14T08:20:49.334Z","agent":"pre_check_batch","verdict":"pass","summary":"Secretscan: 0 finding(s), 1 files scanned, 0 skipped","findings_count":0,"scan_directory":"/Users/butze/Documents/git/image-age-sorter","files_scanned":1,"skipped_files":0},{"task_id":"secretscan","type":"secretscan","timestamp":"2026-04-14T08:29:32.049Z","agent":"pre_check_batch","verdict":"pass","summary":"Secretscan: 0 finding(s), 1 files scanned, 0 skipped","findings_count":0,"scan_directory":"/Users/butze/Documents/git/image-age-sorter","files_scanned":1,"skipped_files":0},{"task_id":"secretscan","type":"secretscan","timestamp":"2026-04-14T09:02:44.951Z","agent":"pre_check_batch","verdict":"pass","summary":"Secretscan: 0 finding(s), 1 files scanned, 0 skipped","findings_count":0,"scan_directory":"/Users/butze/Documents/git/image-age-sorter","files_scanned":1,"skipped_files":0},{"task_id":"secretscan","type":"secretscan","timestamp":"2026-04-14T09:39:53.898Z","agent":"pre_check_batch","verdict":"pass","summary":"Secretscan: 0 finding(s), 1 files scanned, 0 skipped","findings_count":0,"scan_directory":"/Users/butze/Documents/git/image-age-sorter","files_scanned":1,"skipped_files":0},{"task_id":"secretscan","type":"secretscan","timestamp":"2026-04-14T10:06:30.918Z","agent":"pre_check_batch","verdict":"pass","summary":"Secretscan: 0 finding(s), 1 files scanned, 0 skipped","findings_count":0,"scan_directory":"/Users/butze/Documents/git/image-age-sorter","files_scanned":1,"skipped_files":0},{"task_id":"secretscan","type":"secretscan","timestamp":"2026-04-14T10:46:33.253Z","agent":"pre_check_batch","verdict":"pass","summary":"Secretscan: 0 finding(s), 1 files scanned, 0 skipped","findings_count":0,"scan_directory":"/Users/butze/Documents/git/image-age-sorter","files_scanned":1,"skipped_files":0},{"task_id":"secretscan","type":"secretscan","timestamp":"2026-04-14T12:48:49.596Z","agent":"pre_check_batch","verdict":"pass","summary":"Secretscan: 0 finding(s), 3 files scanned, 0 skipped","findings_count":0,"scan_directory":"/Users/butze/Documents/git/image-age-sorter","files_scanned":3,"skipped_files":0},{"task_id":"secretscan","type":"secretscan","timestamp":"2026-04-14T13:16:08.900Z","agent":"pre_check_batch","verdict":"pass","summary":"Secretscan: 0 finding(s), 3 files scanned, 0 skipped","findings_count":0,"scan_directory":"/Users/butze/Documents/git/image-age-sorter","files_scanned":3,"skipped_files":0},{"task_id":"secretscan","type":"secretscan","timestamp":"2026-04-14T13:42:15.555Z","agent":"pre_check_batch","verdict":"pass","summary":"Secretscan: 0 finding(s), 2 files scanned, 0 skipped","findings_count":0,"scan_directory":"/Users/butze/Documents/git/image-age-sorter","files_scanned":2,"skipped_files":0},{"task_id":"secretscan","type":"secretscan","timestamp":"2026-04-14T17:16:05.141Z","agent":"pre_check_batch","verdict":"pass","summary":"Secretscan: 0 finding(s), 1 files scanned, 0 skipped","findings_count":0,"scan_directory":"/Users/butze/Documents/git/image-age-sorter","files_scanned":1,"skipped_files":0},{"task_id":"secretscan","type":"secretscan","timestamp":"2026-04-14T19:55:56.396Z","agent":"pre_check_batch","verdict":"pass","summary":"Secretscan: 0 finding(s), 1 files scanned, 0 skipped","findings_count":0,"scan_directory":"/Users/butze/Documents/git/image-age-sorter","files_scanned":1,"skipped_files":0},{"task_id":"secretscan","type":"secretscan","timestamp":"2026-04-14T20:12:56.233Z","agent":"pre_check_batch","verdict":"pass","summary":"Secretscan: 0 finding(s), 1 files scanned, 0 skipped","findings_count":0,"scan_directory":"/Users/butze/Documents/git/image-age-sorter","files_scanned":1,"skipped_files":0},{"task_id":"secretscan","type":"secretscan","timestamp":"2026-04-14T20:48:08.939Z","agent":"pre_check_batch","verdict":"pass","summary":"Secretscan: 0 finding(s), 1 files scanned, 0 skipped","findings_count":0,"scan_directory":"/Users/butze/Documents/git/image-age-sorter","files_scanned":1,"skipped_files":0},{"task_id":"secretscan","type":"secretscan","timestamp":"2026-04-14T20:55:35.400Z","agent":"pre_check_batch","verdict":"pass","summary":"Secretscan: 0 finding(s), 1 files scanned, 0 skipped","findings_count":0,"scan_directory":"/Users/butze/Documents/git/image-age-sorter","files_scanned":1,"skipped_files":0},{"task_id":"secretscan","type":"secretscan","timestamp":"2026-04-14T21:24:39.727Z","agent":"pre_check_batch","verdict":"pass","summary":"Secretscan: 0 finding(s), 1 files scanned, 0 skipped","findings_count":0,"scan_directory":"/Users/butze/Documents/git/image-age-sorter","files_scanned":1,"skipped_files":0},{"task_id":"secretscan","type":"secretscan","timestamp":"2026-04-14T21:38:42.757Z","agent":"pre_check_batch","verdict":"pass","summary":"Secretscan: 0 finding(s), 1 files scanned, 0 skipped","findings_count":0,"scan_directory":"/Users/butze/Documents/git/image-age-sorter","files_scanned":1,"skipped_files":0},{"task_id":"secretscan","type":"secretscan","timestamp":"2026-04-14T22:13:37.503Z","agent":"pre_check_batch","verdict":"pass","summary":"Secretscan: 0 finding(s), 2 files scanned, 0 skipped","findings_count":0,"scan_directory":"/Users/butze/Documents/git/image-age-sorter","files_scanned":2,"skipped_files":0},{"task_id":"secretscan","type":"secretscan","timestamp":"2026-04-14T22:26:49.877Z","agent":"pre_check_batch","verdict":"pass","summary":"Secretscan: 0 finding(s), 1 files scanned, 0 skipped","findings_count":0,"scan_directory":"/Users/butze/Documents/git/image-age-sorter","files_scanned":1,"skipped_files":0},{"task_id":"secretscan","type":"secretscan","timestamp":"2026-04-14T22:57:13.075Z","agent":"pre_check_batch","verdict":"pass","summary":"Secretscan: 0 finding(s), 3 files scanned, 0 skipped","findings_count":0,"scan_directory":"/Users/butze/Documents/git/image-age-sorter","files_scanned":3,"skipped_files":0},{"task_id":"secretscan","type":"secretscan","timestamp":"2026-04-15T06:10:44.627Z","agent":"pre_check_batch","verdict":"pass","summary":"Secretscan: 0 finding(s), 1 files scanned, 0 skipped","findings_count":0,"scan_directory":"/Users/butze/Documents/git/image-age-sorter","files_scanned":1,"skipped_files":0},{"task_id":"secretscan","type":"secretscan","timestamp":"2026-04-15T09:04:16.180Z","agent":"pre_check_batch","verdict":"pass","summary":"Secretscan: 0 finding(s), 1 files scanned, 0 skipped","findings_count":0,"scan_directory":"/Users/butze/Documents/git/image-age-sorter","files_scanned":1,"skipped_files":0},{"task_id":"secretscan","type":"secretscan","timestamp":"2026-04-15T09:08:52.138Z","agent":"pre_check_batch","verdict":"pass","summary":"Secretscan: 0 finding(s), 1 files scanned, 0 skipped","findings_count":0,"scan_directory":"/Users/butze/Documents/git/image-age-sorter","files_scanned":1,"skipped_files":0}],"created_at":"2026-04-13T22:03:54.110Z","updated_at":"2026-04-15T09:08:52.139Z"}